[
  {
    "id": 3600,
    "stage_id": 25,
    "latitude": 49.48446144371775,
    "longitude": 0.10200294365317049
  },
  {
    "id": 3601,
    "stage_id": 25,
    "latitude": 49.47571857690315,
    "longitude": 0.07706874104906151
  },
  {
    "id": 3602,
    "stage_id": 25,
    "latitude": 49.442405144744754,
    "longitude": 0.05990523673847884
  },
  {
    "id": 3603,
    "stage_id": 25,
    "latitude": 49.4011581125782,
    "longitude": 0.040596294389073306
  },
  {
    "id": 3604,
    "stage_id": 25,
    "latitude": 49.353288833247404,
    "longitude": 0.0009271535993853831
  },
  {
    "id": 3605,
    "stage_id": 25,
    "latitude": 49.33869031270862,
    "longitude": -0.056046145431576565
  },
  {
    "id": 3606,
    "stage_id": 25,
    "latitude": 49.31072360970302,
    "longitude": -0.15306762118723144
  },
  {
    "id": 3607,
    "stage_id": 25,
    "latitude": 49.30466206365409,
    "longitude": -0.17619067560565527
  },
  {
    "id": 3608,
    "stage_id": 25,
    "latitude": 49.29859977183992,
    "longitude": -0.22744280653308968
  },
  {
    "id": 3609,
    "stage_id": 25,
    "latitude": 49.29717751830202,
    "longitude": -0.24141185875818008
  },
  {
    "id": 3610,
    "stage_id": 25,
    "latitude": 49.29616405457699,
    "longitude": -0.24546349608491236
  },
  {
    "id": 3611,
    "stage_id": 25,
    "latitude": 49.292254785001944,
    "longitude": -0.245796507372041
  },
  {
    "id": 3612,
    "stage_id": 25,
    "latitude": 49.287621175138185,
    "longitude": -0.245796507372041
  },
  {
    "id": 3613,
    "stage_id": 25,
    "latitude": 49.28377149348296,
    "longitude": -0.24799481752591562
  },
  {
    "id": 3614,
    "stage_id": 25,
    "latitude": 49.27377048583804,
    "longitude": -0.25063792986344235
  },
  {
    "id": 3615,
    "stage_id": 25,
    "latitude": 49.26089263942967,
    "longitude": -0.25442639088056407
  },
  {
    "id": 3616,
    "stage_id": 25,
    "latitude": 49.256752617813305,
    "longitude": -0.25997692678937023
  },
  {
    "id": 3617,
    "stage_id": 25,
    "latitude": 49.253819892381216,
    "longitude": -0.2655274626981764
  },
  {
    "id": 3618,
    "stage_id": 25,
    "latitude": 49.24404288245873,
    "longitude": -0.27336869596617247
  },
  {
    "id": 3619,
    "stage_id": 25,
    "latitude": 49.237312874325454,
    "longitude": -0.27839060940747323
  },
  {
    "id": 3620,
    "stage_id": 25,
    "latitude": 49.23207778947861,
    "longitude": -0.2844697677837848
  },
  {
    "id": 3621,
    "stage_id": 25,
    "latitude": 49.22753259558098,
    "longitude": -0.2942492834326338
  },
  {
    "id": 3622,
    "stage_id": 25,
    "latitude": 49.222986983521594,
    "longitude": -0.3023548279343825
  },
  {
    "id": 3623,
    "stage_id": 25,
    "latitude": 49.21861359498854,
    "longitude": -0.30764105260943597
  },
  {
    "id": 3624,
    "stage_id": 25,
    "latitude": 49.20716038892297,
    "longitude": -0.31363210724116325
  },
  {
    "id": 3625,
    "stage_id": 25,
    "latitude": 49.1999072381999,
    "longitude": -0.3182135019595428
  },
  {
    "id": 3626,
    "stage_id": 25,
    "latitude": 49.19368940510452,
    "longitude": -0.3220900667212487
  },
  {
    "id": 3627,
    "stage_id": 25,
    "latitude": 49.186664616399014,
    "longitude": -0.3265833576950441
  },
  {
    "id": 3628,
    "stage_id": 25,
    "latitude": 49.1965105558763,
    "longitude": -0.32068040680790105
  },
  {
    "id": 3629,
    "stage_id": 25,
    "latitude": 49.20485791664993,
    "longitude": -0.31548228587743177
  },
  {
    "id": 3630,
    "stage_id": 25,
    "latitude": 49.218717891529565,
    "longitude": -0.3076404471790343
  },
  {
    "id": 3631,
    "stage_id": 25,
    "latitude": 49.22568058931827,
    "longitude": -0.29786093153018534
  },
  {
    "id": 3632,
    "stage_id": 25,
    "latitude": 49.23114648277408,
    "longitude": -0.2871122746909099
  },
  {
    "id": 3633,
    "stage_id": 25,
    "latitude": 49.23551876216473,
    "longitude": -0.27962345640125075
  },
  {
    "id": 3634,
    "stage_id": 25,
    "latitude": 49.25246963598633,
    "longitude": -0.2667226034149589
  },
  {
    "id": 3635,
    "stage_id": 25,
    "latitude": 49.25862257655143,
    "longitude": -0.25676688027694144
  },
  {
    "id": 3636,
    "stage_id": 25,
    "latitude": 49.26454477613325,
    "longitude": -0.2531546267489882
  },
  {
    "id": 3637,
    "stage_id": 25,
    "latitude": 49.281970091873404,
    "longitude": -0.24845376246073034
  },
  {
    "id": 3638,
    "stage_id": 25,
    "latitude": 49.286970017855765,
    "longitude": -0.24748462127030388
  },
  {
    "id": 3639,
    "stage_id": 25,
    "latitude": 49.29059033742331,
    "longitude": -0.24510582016652982
  },
  {
    "id": 3640,
    "stage_id": 25,
    "latitude": 49.294899895047934,
    "longitude": -0.24501771642194559
  },
  {
    "id": 3641,
    "stage_id": 25,
    "latitude": 49.30265614935402,
    "longitude": -0.2422865003398346
  },
  {
    "id": 3642,
    "stage_id": 25,
    "latitude": 49.355940864196896,
    "longitude": -0.37419543233399366
  },
  {
    "id": 3643,
    "stage_id": 25,
    "latitude": 49.361682515351106,
    "longitude": -0.4711649336954006
  },
  {
    "id": 3644,
    "stage_id": 25,
    "latitude": 49.365701272320166,
    "longitude": -0.5707790578212095
  },
  {
    "id": 3645,
    "stage_id": 25,
    "latitude": 49.37545974327375,
    "longitude": -0.7303379646067975
  },
  {
    "id": 3646,
    "stage_id": 25,
    "latitude": 49.413900739076155,
    "longitude": -0.8960676578426566
  },
  {
    "id": 3647,
    "stage_id": 25,
    "latitude": 49.42250281066492,
    "longitude": -0.981577127224988
  },
  {
    "id": 3648,
    "stage_id": 25,
    "latitude": 49.47007368926771,
    "longitude": -1.1190975109738925
  },
  {
    "id": 3649,
    "stage_id": 25,
    "latitude": 49.512447363733884,
    "longitude": -1.1473068204608474
  },
  {
    "id": 3650,
    "stage_id": 25,
    "latitude": 49.595370527128324,
    "longitude": -1.1763976708692692
  },
  {
    "id": 3651,
    "stage_id": 25,
    "latitude": 49.68328651867435,
    "longitude": -1.2222377987855706
  },
  {
    "id": 3652,
    "stage_id": 25,
    "latitude": 49.748834570536104,
    "longitude": -1.2063700621991587
  },
  {
    "id": 3653,
    "stage_id": 25,
    "latitude": 49.887049559831894,
    "longitude": -1.2213562578641033
  },
  {
    "id": 3654,
    "stage_id": 25,
    "latitude": 49.98180799818755,
    "longitude": -1.2178300941782336
  },
  {
    "id": 3655,
    "stage_id": 25,
    "latitude": 50.05431110920338,
    "longitude": -1.2345793716861133
  },
  {
    "id": 3656,
    "stage_id": 25,
    "latitude": 50.16372263045625,
    "longitude": -1.2319347489217114
  },
  {
    "id": 3657,
    "stage_id": 25,
    "latitude": 50.297935089297425,
    "longitude": -1.2363424535290481
  },
  {
    "id": 3658,
    "stage_id": 25,
    "latitude": 50.364337368436196,
    "longitude": -1.2777748768380128
  },
  {
    "id": 3659,
    "stage_id": 25,
    "latitude": 50.46601142704489,
    "longitude": -1.3103918909323042
  },
  {
    "id": 3660,
    "stage_id": 25,
    "latitude": 50.55069319541829,
    "longitude": -1.2936426134244248
  },
  {
    "id": 3661,
    "stage_id": 25,
    "latitude": 50.57365280650609,
    "longitude": -1.2292901261573093
  },
  {
    "id": 3662,
    "stage_id": 25,
    "latitude": 50.60163719533011,
    "longitude": -1.110282101759219
  },
  {
    "id": 3663,
    "stage_id": 25,
    "latitude": 50.6458186337797,
    "longitude": -1.0811912513507969
  },
  {
    "id": 3664,
    "stage_id": 25,
    "latitude": 50.680463604840355,
    "longitude": -1.041521909884767
  },
  {
    "id": 3665,
    "stage_id": 25,
    "latitude": 50.72010629303554,
    "longitude": -0.9798140453820532
  },
  {
    "id": 3666,
    "stage_id": 25,
    "latitude": 50.738520361238386,
    "longitude": -0.8801999212562442
  },
  {
    "id": 3667,
    "stage_id": 25,
    "latitude": 50.698334880157745,
    "longitude": -0.774415010680164
  },
  {
    "id": 3668,
    "stage_id": 25,
    "latitude": 50.742983287792356,
    "longitude": -0.6765639683972897
  },
  {
    "id": 3669,
    "stage_id": 25,
    "latitude": 50.77086694289244,
    "longitude": -0.519649684376104
  },
  {
    "id": 3670,
    "stage_id": 25,
    "latitude": 50.78647453377272,
    "longitude": -0.404167823663883
  },
  {
    "id": 3671,
    "stage_id": 25,
    "latitude": 50.78870376440031,
    "longitude": -0.228741180291883
  },
  {
    "id": 3672,
    "stage_id": 25,
    "latitude": 50.78703185139514,
    "longitude": -0.06389302797749134
  },
  {
    "id": 3673,
    "stage_id": 25,
    "latitude": 50.741309740178764,
    "longitude": 0.13004597474532265
  },
  {
    "id": 3674,
    "stage_id": 25,
    "latitude": 50.71452484333486,
    "longitude": 0.24817245822194564
  },
  {
    "id": 3675,
    "stage_id": 25,
    "latitude": 50.73349906044541,
    "longitude": 0.2966572089026491
  },
  {
    "id": 3676,
    "stage_id": 25,
    "latitude": 50.78368784600403,
    "longitude": 0.39979749671432735
  },
  {
    "id": 3677,
    "stage_id": 25,
    "latitude": 50.82101566411666,
    "longitude": 0.44122992002329214
  },
  {
    "id": 3678,
    "stage_id": 25,
    "latitude": 50.83437956926804,
    "longitude": 0.5426071259920359
  },
  {
    "id": 3679,
    "stage_id": 25,
    "latitude": 50.85274869264401,
    "longitude": 0.6695490186833323
  },
  {
    "id": 3680,
    "stage_id": 25,
    "latitude": 50.88890914999507,
    "longitude": 0.7365461287148498
  },
  {
    "id": 3681,
    "stage_id": 25,
    "latitude": 50.90392140182027,
    "longitude": 0.8352787119191916
  },
  {
    "id": 3682,
    "stage_id": 25,
    "latitude": 50.90058576407807,
    "longitude": 0.9683913910607592
  },
  {
    "id": 3683,
    "stage_id": 25,
    "latitude": 50.928375443729294,
    "longitude": 1.0450854512284173
  },
  {
    "id": 3684,
    "stage_id": 25,
    "latitude": 50.9961126344179,
    "longitude": 1.043322369385483
  },
  {
    "id": 3685,
    "stage_id": 25,
    "latitude": 51.05433197850414,
    "longitude": 1.170264262076779
  },
  {
    "id": 3686,
    "stage_id": 25,
    "latitude": 51.091443256510104,
    "longitude": 1.2945615320036734
  },
  {
    "id": 3687,
    "stage_id": 25,
    "latitude": 51.11635203646651,
    "longitude": 1.412688015480296
  },
  {
    "id": 3688,
    "stage_id": 25,
    "latitude": 51.18381499821322,
    "longitude": 1.4391342431243161
  },
  {
    "id": 3689,
    "stage_id": 25,
    "latitude": 51.257248357518506,
    "longitude": 1.4417788658887183
  },
  {
    "id": 3690,
    "stage_id": 25,
    "latitude": 51.303015840581935,
    "longitude": 1.4453050295745875
  },
  {
    "id": 3691,
    "stage_id": 25,
    "latitude": 51.34818713652365,
    "longitude": 1.480566666433281
  },
  {
    "id": 3692,
    "stage_id": 25,
    "latitude": 51.39991414123017,
    "longitude": 1.4849743710406176
  },
  {
    "id": 3693,
    "stage_id": 25,
    "latitude": 51.41751000115369,
    "longitude": 1.4400157840457837
  },
  {
    "id": 3694,
    "stage_id": 25,
    "latitude": 51.41751000115369,
    "longitude": 1.3404016599199748
  },
  {
    "id": 3695,
    "stage_id": 25,
    "latitude": 51.41311167097672,
    "longitude": 1.2116966853857438
  },
  {
    "id": 3696,
    "stage_id": 25,
    "latitude": 51.39661416363194,
    "longitude": 1.0494931558357539
  },
  {
    "id": 3697,
    "stage_id": 25,
    "latitude": 51.413661485391884,
    "longitude": 0.9780883411968999
  },
  {
    "id": 3698,
    "stage_id": 25,
    "latitude": 51.43894580099962,
    "longitude": 0.8573172349558749
  },
  {
    "id": 3699,
    "stage_id": 25,
    "latitude": 51.47135520679748,
    "longitude": 0.8167663525683774
  },
  {
    "id": 3700,
    "stage_id": 25,
    "latitude": 51.49166801089916,
    "longitude": 0.7788600929452818
  },
  {
    "id": 3701,
    "stage_id": 25,
    "latitude": 51.51087449919112,
    "longitude": 0.7100999010708298
  },
  {
    "id": 3702,
    "stage_id": 25,
    "latitude": 51.50374160558073,
    "longitude": 0.6422212501178448
  },
  {
    "id": 3703,
    "stage_id": 25,
    "latitude": 51.49990035418631,
    "longitude": 0.5743425991648601
  },
  {
    "id": 3704,
    "stage_id": 25,
    "latitude": 51.502095394629265,
    "longitude": 0.5320286349344279
  },
  {
    "id": 3705,
    "stage_id": 25,
    "latitude": 51.49605877900993,
    "longitude": 0.4853069660966591
  },
  {
    "id": 3706,
    "stage_id": 25,
    "latitude": 51.484532110688605,
    "longitude": 0.45533457476676964
  },
  {
    "id": 3707,
    "stage_id": 25,
    "latitude": 51.4642161276758,
    "longitude": 0.44916378831649834
  },
  {
    "id": 3708,
    "stage_id": 25,
    "latitude": 51.44993461825541,
    "longitude": 0.4209544788295436
  },
  {
    "id": 3709,
    "stage_id": 25,
    "latitude": 51.44883585552168,
    "longitude": 0.36894356446297083
  },
  {
    "id": 3710,
    "stage_id": 25,
    "latitude": 51.45158271277771,
    "longitude": 0.33191884576134256
  },
  {
    "id": 3711,
    "stage_id": 25,
    "latitude": 51.466412886377015,
    "longitude": 0.32045881378226726
  },
  {
    "id": 3712,
    "stage_id": 25,
    "latitude": 51.47025695963666,
    "longitude": 0.3107618636461265
  },
  {
    "id": 3713,
    "stage_id": 25,
    "latitude": 51.46256848924824,
    "longitude": 0.2957756679811819
  },
  {
    "id": 3714,
    "stage_id": 25,
    "latitude": 51.457075931516414,
    "longitude": 0.2799079313947698
  },
  {
    "id": 3715,
    "stage_id": 25,
    "latitude": 51.46311770866717,
    "longitude": 0.2578694083580864
  },
  {
    "id": 3716,
    "stage_id": 25,
    "latitude": 51.47794413458837,
    "longitude": 0.22877855794966429
  },
  {
    "id": 3717,
    "stage_id": 25,
    "latitude": 51.484532110688605,
    "longitude": 0.21026619859885026
  },
  {
    "id": 3718,
    "stage_id": 25,
    "latitude": 51.48233622439548,
    "longitude": 0.18558305279776488
  },
  {
    "id": 3719,
    "stage_id": 25,
    "latitude": 51.49057025278972,
    "longitude": 0.17853072542602622
  },
  {
    "id": 3720,
    "stage_id": 25,
    "latitude": 51.508131210719455,
    "longitude": 0.16707069344695086
  },
  {
    "id": 3721,
    "stage_id": 25,
    "latitude": 51.51204558788635,
    "longitude": 0.1409361569502314
  },
  {
    "id": 3722,
    "stage_id": 25,
    "latitude": 51.515272768809865,
    "longitude": 0.1326550331092075
  },
  {
    "id": 3723,
    "stage_id": 25,
    "latitude": 51.51518292619323,
    "longitude": 0.1248590348473274
  },
  {
    "id": 3724,
    "stage_id": 25,
    "latitude": 51.51320634379462,
    "longitude": 0.11042200102903094
  },
  {
    "id": 3725,
    "stage_id": 25,
    "latitude": 51.512307868896755,
    "longitude": 0.0987280036362108
  },
  {
    "id": 3726,
    "stage_id": 25,
    "latitude": 51.510510865938386,
    "longitude": 0.08919956131613513
  },
  {
    "id": 3727,
    "stage_id": 25,
    "latitude": 51.50422079736299,
    "longitude": 0.08212541474516986
  },
  {
    "id": 3728,
    "stage_id": 25,
    "latitude": 51.49900836841934,
    "longitude": 0.07591749020330239
  },
  {
    "id": 3729,
    "stage_id": 25,
    "latitude": 51.49703108424063,
    "longitude": 0.06913208430870305
  },
  {
    "id": 3730,
    "stage_id": 25,
    "latitude": 51.49649181003187,
    "longitude": 0.060325493679542194
  },
  {
    "id": 3731,
    "stage_id": 25,
    "latitude": 51.4966715688104,
    "longitude": 0.04776527425762428
  },
  {
    "id": 3732,
    "stage_id": 25,
    "latitude": 51.49703108424063,
    "longitude": 0.036071276864804144
  },
  {
    "id": 3733,
    "stage_id": 25,
    "latitude": 51.49685132687998,
    "longitude": 0.027986537926558128
  },
  {
    "id": 3734,
    "stage_id": 25,
    "latitude": 51.497390596835174,
    "longitude": 0.01975742865012914
  },
  {
    "id": 3735,
    "stage_id": 25,
    "latitude": 51.501142943333946,
    "longitude": 0.014271355799176492
  },
  {
    "id": 3736,
    "stage_id": 25,
    "latitude": 51.50473761734591,
    "longitude": 0.008640912610040876
  },
  {
    "id": 3737,
    "stage_id": 25,
    "latitude": 51.50671456718845,
    "longitude": 0.0015667660390756054
  },
  {
    "id": 3738,
    "stage_id": 25,
    "latitude": 51.50392884041557,
    "longitude": -0.003486195797328158
  },
  {
    "id": 3739,
    "stage_id": 25,
    "latitude": 51.50060371777539,
    "longitude": -0.004641158502791871
  },
  {
    "id": 3740,
    "stage_id": 25,
    "latitude": 51.49449204887364,
    "longitude": -0.002619973768230372
  },
  {
    "id": 3741,
    "stage_id": 25,
    "latitude": 51.489098719266195,
    "longitude": 0.0004118033336118848
  },
  {
    "id": 3742,
    "stage_id": 25,
    "latitude": 51.48622201591124,
    "longitude": -0.003053084782779261
  },
  {
    "id": 3743,
    "stage_id": 25,
    "latitude": 51.4846037905138,
    "longitude": -0.012004045750123067
  },
  {
    "id": 3744,
    "stage_id": 25,
    "latitude": 51.48469369343135,
    "longitude": -0.01980004401200316
  },
  {
    "id": 3745,
    "stage_id": 25,
    "latitude": 51.489907759383584,
    "longitude": -0.026585449906602495
  },
  {
    "id": 3746,
    "stage_id": 25,
    "latitude": 51.49449204887364,
    "longitude": -0.028895375317529934
  },
  {
    "id": 3747,
    "stage_id": 25,
    "latitude": 51.502760581729234,
    "longitude": -0.030339078699359576
  },
  {
    "id": 3748,
    "stage_id": 25,
    "latitude": 51.50653484801987,
    "longitude": -0.031349671066640335
  },
  {
    "id": 3749,
    "stage_id": 25,
    "latitude": 51.508595189813946,
    "longitude": -0.03971289059721932
  },
  {
    "id": 3750,
    "stage_id": 25,
    "latitude": 51.50616902136858,
    "longitude": -0.047220148182733485
  },
  {
    "id": 3751,
    "stage_id": 25,
    "latitude": 51.50320352893456,
    "longitude": -0.054005554077332825
  },
  {
    "id": 3752,
    "stage_id": 25,
    "latitude": 51.50131629690142,
    "longitude": -0.06064658963374919
  },
  {
    "id": 3753,
    "stage_id": 25,
    "latitude": 51.50248459261368,
    "longitude": -0.06757636586653148
  },
  {
    "id": 3754,
    "stage_id": 25,
    "latitude": 51.50464136754982,
    "longitude": -0.07277369804111822
  },
  {
    "id": 3755,
    "stage_id": 25,
    "latitude": 51.50661832156828,
    "longitude": -0.08013658528844941
  },
  {
    "id": 3756,
    "stage_id": 25,
    "latitude": 51.50796619558503,
    "longitude": -0.08937628693215917
  },
  {
    "id": 3757,
    "stage_id": 25,
    "latitude": 51.508954611188955,
    "longitude": -0.09543984113584368
  },
  {
    "id": 3758,
    "stage_id": 25,
    "latitude": 51.50985315222147,
    "longitude": -0.10193650635407707
  },
  {
    "id": 3759,
    "stage_id": 25,
    "latitude": 51.509763298915686,
    "longitude": -0.1075669495432127
  },
  {
    "id": 3760,
    "stage_id": 25,
    "latitude": 51.509224175359435,
    "longitude": -0.11449672577599501
  },
  {
    "id": 3761,
    "stage_id": 25,
    "latitude": 51.507876338557764,
    "longitude": -0.11853909524511802
  },
  {
    "id": 3762,
    "stage_id": 25,
    "latitude": 51.50541457483712,
    "longitude": -0.12179625792717062
  },
  {
    "id": 3763,
    "stage_id": 25,
    "latitude": 51.50217942904814,
    "longitude": -0.12064129522170693
  },
  {
    "id": 3764,
    "stage_id": 25,
    "latitude": 51.49283216212123,
    "longitude": -0.12323996130900026
  },
  {
    "id": 3765,
    "stage_id": 25,
    "latitude": 51.48779822438257,
    "longitude": -0.1256942570581107
  },
  {
    "id": 3766,
    "stage_id": 25,
    "latitude": 51.485101243380086,
    "longitude": -0.13204655193816112
  },
  {
    "id": 3767,
    "stage_id": 25,
    "latitude": 51.48339307290351,
    "longitude": -0.14056440189095604
  },
  {
    "id": 3768,
    "stage_id": 25,
    "latitude": 51.4846517310373,
    "longitude": -0.14864914082920205
  },
  {
    "id": 3769,
    "stage_id": 25,
    "latitude": 51.48303344991288,
    "longitude": -0.1614981009274859
  },
  {
    "id": 3770,
    "stage_id": 25,
    "latitude": 51.481774747112155,
    "longitude": -0.16943846952754896
  },
  {
    "id": 3771,
    "stage_id": 25,
    "latitude": 51.479257237286106,
    "longitude": -0.1755020237312335
  },
  {
    "id": 3772,
    "stage_id": 25,
    "latitude": 51.47602023473968,
    "longitude": -0.17723446778942906
  },
  {
    "id": 3773,
    "stage_id": 25,
    "latitude": 51.47359233207044,
    "longitude": -0.17838943049489278
  }
]