[
  {
    "id": 2098,
    "stage_id": 16,
    "latitude": 42.09707624579872,
    "longitude": 11.778862348589064
  },
  {
    "id": 2099,
    "stage_id": 16,
    "latitude": 42.10707708078621,
    "longitude": 11.764623360139975
  },
  {
    "id": 2100,
    "stage_id": 16,
    "latitude": 42.110570264900275,
    "longitude": 11.756051286451179
  },
  {
    "id": 2101,
    "stage_id": 16,
    "latitude": 42.11997403457582,
    "longitude": 11.74711701246567
  },
  {
    "id": 2102,
    "stage_id": 16,
    "latitude": 42.15980857570247,
    "longitude": 11.705056101091062
  },
  {
    "id": 2103,
    "stage_id": 16,
    "latitude": 42.21080806120392,
    "longitude": 11.685106136949916
  },
  {
    "id": 2104,
    "stage_id": 16,
    "latitude": 42.25143035643333,
    "longitude": 11.647201205081737
  },
  {
    "id": 2105,
    "stage_id": 16,
    "latitude": 42.28649220734789,
    "longitude": 11.57837382879478
  },
  {
    "id": 2106,
    "stage_id": 16,
    "latitude": 42.33628339234832,
    "longitude": 11.522513929199569
  },
  {
    "id": 2107,
    "stage_id": 16,
    "latitude": 42.36061141341014,
    "longitude": 11.429746595943234
  },
  {
    "id": 2108,
    "stage_id": 16,
    "latitude": 42.36577069228184,
    "longitude": 11.35293923399982
  },
  {
    "id": 2109,
    "stage_id": 16,
    "latitude": 42.38271962554484,
    "longitude": 11.306056818268125
  },
  {
    "id": 2110,
    "stage_id": 16,
    "latitude": 42.36835017284139,
    "longitude": 11.232241950945882
  },
  {
    "id": 2111,
    "stage_id": 16,
    "latitude": 42.34697413698581,
    "longitude": 11.196830764595347
  },
  {
    "id": 2112,
    "stage_id": 16,
    "latitude": 42.31668996562291,
    "longitude": 11.166226081046212
  },
  {
    "id": 2113,
    "stage_id": 16,
    "latitude": 42.26828361937703,
    "longitude": 11.14623089047879
  },
  {
    "id": 2114,
    "stage_id": 16,
    "latitude": 42.22253235726566,
    "longitude": 11.129871189105446
  },
  {
    "id": 2115,
    "stage_id": 16,
    "latitude": 42.24541213566664,
    "longitude": 11.035348470059446
  },
  {
    "id": 2116,
    "stage_id": 16,
    "latitude": 42.291146807760725,
    "longitude": 11.015353279492023
  },
  {
    "id": 2117,
    "stage_id": 16,
    "latitude": 42.343566304019845,
    "longitude": 10.946278984804565
  },
  {
    "id": 2118,
    "stage_id": 16,
    "latitude": 42.42815170127727,
    "longitude": 10.888111157699335
  },
  {
    "id": 2119,
    "stage_id": 16,
    "latitude": 42.483138115003925,
    "longitude": 10.79358843865334
  },
  {
    "id": 2120,
    "stage_id": 16,
    "latitude": 42.52869998254425,
    "longitude": 10.617267212740613
  },
  {
    "id": 2121,
    "stage_id": 16,
    "latitude": 42.57556721672995,
    "longitude": 10.431857263842696
  },
  {
    "id": 2122,
    "stage_id": 16,
    "latitude": 42.59028965010296,
    "longitude": 10.122840682346164
  },
  {
    "id": 2123,
    "stage_id": 16,
    "latitude": 42.629086672787565,
    "longitude": 10.131929405331357
  },
  {
    "id": 2124,
    "stage_id": 16,
    "latitude": 42.6611762777481,
    "longitude": 10.168284297272125
  },
  {
    "id": 2125,
    "stage_id": 16,
    "latitude": 42.67320561202217,
    "longitude": 10.295526419064814
  },
  {
    "id": 2126,
    "stage_id": 16,
    "latitude": 42.722635083648214,
    "longitude": 10.330063566408544
  },
  {
    "id": 2127,
    "stage_id": 16,
    "latitude": 42.67988756963072,
    "longitude": 10.386413648916735
  },
  {
    "id": 2128,
    "stage_id": 16,
    "latitude": 42.67053262780155,
    "longitude": 10.502749303127192
  },
  {
    "id": 2129,
    "stage_id": 16,
    "latitude": 42.81204235929067,
    "longitude": 10.511838026112382
  },
  {
    "id": 2130,
    "stage_id": 16,
    "latitude": 42.88400802825197,
    "longitude": 10.504567047724226
  },
  {
    "id": 2131,
    "stage_id": 16,
    "latitude": 42.927945770052986,
    "longitude": 10.359147479961159
  },
  {
    "id": 2132,
    "stage_id": 16,
    "latitude": 42.9678619943852,
    "longitude": 10.295526419064817
  },
  {
    "id": 2133,
    "stage_id": 16,
    "latitude": 42.9678619943852,
    "longitude": 10.133747149928398
  },
  {
    "id": 2134,
    "stage_id": 16,
    "latitude": 43.00243511681009,
    "longitude": 10.070126089032053
  },
  {
    "id": 2135,
    "stage_id": 16,
    "latitude": 43.042303018885804,
    "longitude": 9.973785625389018
  },
  {
    "id": 2136,
    "stage_id": 16,
    "latitude": 43.05691476276465,
    "longitude": 9.866538694163753
  },
  {
    "id": 2137,
    "stage_id": 16,
    "latitude": 43.133900935149626,
    "longitude": 9.917435542880826
  },
  {
    "id": 2138,
    "stage_id": 16,
    "latitude": 43.23330851050295,
    "longitude": 9.975603369986056
  },
  {
    "id": 2139,
    "stage_id": 16,
    "latitude": 43.31139537199715,
    "longitude": 10.131929405331359
  },
  {
    "id": 2140,
    "stage_id": 16,
    "latitude": 43.373528458675,
    "longitude": 10.11920519315209
  },
  {
    "id": 2141,
    "stage_id": 16,
    "latitude": 43.461991213157575,
    "longitude": 10.115569703958013
  },
  {
    "id": 2142,
    "stage_id": 16,
    "latitude": 43.54505470230686,
    "longitude": 10.090121279599474
  },
  {
    "id": 2143,
    "stage_id": 16,
    "latitude": 43.65299788230658,
    "longitude": 10.10648098097282
  },
  {
    "id": 2144,
    "stage_id": 16,
    "latitude": 43.779124293527275,
    "longitude": 10.091939024196513
  },
  {
    "id": 2145,
    "stage_id": 16,
    "latitude": 43.89057711370174,
    "longitude": 10.079214812017245
  },
  {
    "id": 2146,
    "stage_id": 16,
    "latitude": 43.9586573859155,
    "longitude": 9.990145326762361
  },
  {
    "id": 2147,
    "stage_id": 16,
    "latitude": 44.034501152462354,
    "longitude": 9.90107584150748
  },
  {
    "id": 2148,
    "stage_id": 16,
    "latitude": 44.00051421046189,
    "longitude": 9.873809672551905
  },
  {
    "id": 2149,
    "stage_id": 16,
    "latitude": 44.00443677489429,
    "longitude": 9.779286953505908
  },
  {
    "id": 2150,
    "stage_id": 16,
    "latitude": 44.072389809603294,
    "longitude": 9.691578489854837
  },
  {
    "id": 2151,
    "stage_id": 16,
    "latitude": 44.100802735068385,
    "longitude": 9.660040283303122
  },
  {
    "id": 2152,
    "stage_id": 16,
    "latitude": 44.1253650699534,
    "longitude": 9.609258425296124
  },
  {
    "id": 2153,
    "stage_id": 16,
    "latitude": 44.163723280567126,
    "longitude": 9.561149296657915
  },
  {
    "id": 2154,
    "stage_id": 16,
    "latitude": 44.20332213795879,
    "longitude": 9.483478389011236
  },
  {
    "id": 2155,
    "stage_id": 16,
    "latitude": 44.21979743348933,
    "longitude": 9.459423824692129
  },
  {
    "id": 2156,
    "stage_id": 16,
    "latitude": 44.23933192546312,
    "longitude": 9.402761962073795
  },
  {
    "id": 2157,
    "stage_id": 16,
    "latitude": 44.24928819092523,
    "longitude": 9.355187379309344
  },
  {
    "id": 2158,
    "stage_id": 16,
    "latitude": 44.27914687690179,
    "longitude": 9.328460085621447
  },
  {
    "id": 2159,
    "stage_id": 16,
    "latitude": 44.30248733253049,
    "longitude": 9.311354617661197
  },
  {
    "id": 2160,
    "stage_id": 16,
    "latitude": 44.29866166398983,
    "longitude": 9.275540044119417
  },
  {
    "id": 2161,
    "stage_id": 16,
    "latitude": 44.27493695514323,
    "longitude": 9.238656378830123
  },
  {
    "id": 2162,
    "stage_id": 16,
    "latitude": 44.28986168033063,
    "longitude": 9.16381995650402
  },
  {
    "id": 2163,
    "stage_id": 16,
    "latitude": 44.31740505795494,
    "longitude": 9.083638075440335
  },
  {
    "id": 2164,
    "stage_id": 16,
    "latitude": 44.347229133938015,
    "longitude": 9.065463515732569
  },
  {
    "id": 2165,
    "stage_id": 16,
    "latitude": 44.36748555713427,
    "longitude": 9.020027116463147
  },
  {
    "id": 2166,
    "stage_id": 16,
    "latitude": 44.374745588587984,
    "longitude": 8.953208882243416
  },
  {
    "id": 2167,
    "stage_id": 16,
    "latitude": 44.38566880797279,
    "longitude": 8.909500478162327
  },
  {
    "id": 2168,
    "stage_id": 16,
    "latitude": 44.392358273472496,
    "longitude": 8.873584638229284
  },
  {
    "id": 2169,
    "stage_id": 16,
    "latitude": 44.40464305509337,
    "longitude": 8.826970462997036
  },
  {
    "id": 2170,
    "stage_id": 16,
    "latitude": 44.41105741587657,
    "longitude": 8.80863045962697
  },
  {
    "id": 2171,
    "stage_id": 16,
    "latitude": 44.41992718128347,
    "longitude": 8.815316919188973
  }
]